fcpgtools/__init__.py
fcpgtools/custom_types.py
fcpgtools/terrainengine/__init__.py
fcpgtools/terrainengine/engine_validator.py
fcpgtools/terrainengine/protocols.py
fcpgtools/terrainengine/pysheds_engine.py
fcpgtools/terrainengine/taudem_engine.py
fcpgtools/tools.py
fcpgtools/tools_deprecated.py
fcpgtools/utilities.py
fcpgtools-2.0.5.dist-info/LICENSE.md
fcpgtools-2.0.5.dist-info/METADATA
fcpgtools-2.0.5.dist-info/WHEEL
fcpgtools-2.0.5.dist-info/RECORD
