Metadata-Version: 2.3
Name: fcpgtools
Version: 2.0.5
Summary: Tools to create Flow-Conditioned Parameter Grids (FCPGs) from Flow Direction Rasters (FDRs) and arbitrary rasterized parameter data.
Keywords: hydrology,terrain,machine-learning,raster,flow-statistics
Author: Theodore Barnhart
Author-email: tbarnhart@usgs.gov
Maintainer: Anders Hopkins
Maintainer-email: ahopkins@usgs.gov
Requires-Python: >=3.9,<4.0
Classifier: Development Status :: 5 - Production/Stable
Classifier: License :: OSI Approved :: MIT License
Classifier: Natural Language :: English
Classifier: Operating System :: Microsoft :: Windows
Classifier: Operating System :: POSIX :: Linux
Classifier: Programming Language :: Python :: 3
Classifier: Programming Language :: Python :: 3.9
Classifier: Programming Language :: Python :: 3.10
Classifier: Programming Language :: Python :: 3.11
Classifier: Programming Language :: Python :: 3.12
Classifier: Programming Language :: Python :: 3.13
Classifier: Topic :: Scientific/Engineering
Classifier: Topic :: Software Development :: Libraries :: Python Modules
Requires-Dist: descartes (>=1.1.0,<2.0.0)
Requires-Dist: geopandas (>=0.14.2,<0.15.0)
Requires-Dist: numba (>=0.57.0,<0.58.0)
Requires-Dist: numpy (>=1.23.0,<2.0.0)
Requires-Dist: pysheds (>=0.3.3,<0.4.0)
Requires-Dist: pytest (>=8.0.0,<9.0.0)
Requires-Dist: rasterio (>=1.2.0,<2.0.0)
Requires-Dist: rioxarray (>=0.14.0,<0.15.0)
Requires-Dist: xarray (>=2023.1.0,<2024.0.0)
Project-URL: Homepage, https://usgs.github.io/water-fcpg-tools/
Project-URL: Repository, https://code.usgs.gov/StreamStats/data-preparation/cpg/FCPGtools
